Metadata-Version: 2.1
Name: blacksheep-messages
Version: 1.0.3
Summary: Extension for BlackSheep that similiar with flask flashes messages
Home-page: https://github.com/riordanz/BlackSheep-Messages
Author: Riordan Ganezo
Author-email: black.ganezo@gmail.com
License: MIT
Keywords: blacksheep flask flashes message messages
Platform: UNKNOWN
Classifier: Development Status :: 3 - Alpha
Classifier: License :: OSI Approved :: MIT License
Classifier: Programming Language :: Python :: 3
Classifier: Programming Language :: Python :: 3.7
Classifier: Programming Language :: Python :: 3.8
Classifier: Programming Language :: Python :: 3.9
Classifier: Programming Language :: Python :: 3.10
Classifier: Operating System :: OS Independent
License-File: LICENSE
